{
  "UnsupportedOSBuild": "Baseline supports Windows 10 (1903 and later) and Windows 11. Your OS is {0}.",
  "UnsupportedWindowsTerminal": "Windows Terminal 버전이 1.20 미만입니다. Microsoft Store에서 업데이트한 후 다시 시도하세요.",
  "UpdateWarning": "Your Windows build: {0}.{1}. Supported builds: {2} and higher. Run Windows Update and try again.",
  "UnsupportedLanguageMode": "PowerShell 세션이 제한된 언어 모드에서 실행 중입니다.",
  "LoggedInUserNotAdmin": "로그인한 사용자에게 관리자 권한이 없습니다.",
  "UnsupportedPowerShell": "PowerShell {0}.{1}을 통해 스크립트를 실행하려고 합니다. 적절한 PowerShell 버전에서 스크립트를 실행하세요.",
  "UnsupportedHost": "이 스크립트는 {0}을 통한 실행을 지원하지 않습니다.",
  "Win10TweakerWarning": "Win 10 Tweaker 백도어를 통해 Windows가 트로이 목마에 감염되었습니다. 정품 ISO 이미지만 사용하여 Windows를 다시 설치하세요.",
  "TweakerWarning": "{0} 사용으로 인해 Windows 안정성이 손상되었을 수 있습니다. 정품 ISO 이미지만 사용하여 Windows를 다시 설치하세요.",
  "Bin": "\"{0}\" 폴더에 파일이 없습니다. 아카이브를 다시 다운로드하세요.",
  "RebootPending": "PC가 재시작 대기 중입니다.",
  "UnsupportedRelease": "새 스크립트 버전이 발견되었습니다. 최신 스크립트만 사용하세요.",
  "KeyboardArrows": "키보드의 화살표 키 {0} 및 {1}을 사용하여 답변을 선택하세요",
  "CustomizationWarning": "Baseline | Windows Utility를 실행하기 전에 {0} 프리셋 파일의 모든 기능을 사용자 정의했습니까?",
  "WindowsComponentBroken": "{0}이(가) 손상되었거나 Windows에서 제거되었습니다. 정품 ISO 이미지만 사용하여 Windows를 다시 설치하세요.",
  "ControlledFolderAccessDisabled": "제어된 폴더 액세스가 비활성화되었습니다.",
  "InitialActionsCheckFailed": "{0} 프리셋 파일에서 InitialActions 함수를 로드할 수 없습니다. 프리셋 파일을 확인하고 다시 시도하세요.",
  "ScheduledTasks": "예약된 작업",
  "OneDriveUninstalling": "OneDrive를 제거하는 중...",
  "OneDriveInstalling": "OneDrive를 설치하는 중...",
  "OneDriveDownloading": "OneDrive를 다운로드하는 중...",
  "OneDriveWarning": "\"WinPrtScrFolder -Desktop\" 기능은 사용자가 OneDrive 제거를 구성한 경우(또는 OneDrive가 이미 제거된 경우)에만 적용됩니다.\n그렇지 않으면 OneDrive의 \"바탕 화면\" 및 \"사진\" 폴더의 백업 기능이 중단됩니다.",
  "WindowsFeaturesTitle": "Windows 기능",
  "OptionalFeaturesTitle": "선택적 기능",
  "EnableHardwareVT": "UEFI에서 가상화를 활성화하세요.",
  "UserShellFolderNotEmpty": "\"{0}\" 폴더에 일부 파일이 남아 있습니다. 새 위치로 수동으로 이동하세요.",
  "UserFolderLocationMove": "사용자 폴더 위치를 C 드라이브 루트로 변경하면 안 됩니다.",
  "DriveSelect": "\"{0}\" 폴더가 생성될 드라이브 루트를 선택하세요.",
  "CurrentUserFolderLocation": "현재 \"{0}\" 폴더 위치: \"{1}\".",
  "UserFolderRequest": "\"{0}\" 폴더의 위치를 변경하시겠습니까?",
  "UserDefaultFolder": "\"{0}\" 폴더의 위치를 기본값으로 변경하시겠습니까?",
  "ReservedStorageIsInUse": "예약된 저장소가 사용 중이므로 이 작업은 지원되지 않습니다\nPC를 재시작한 후 \"{0}\" 기능을 다시 실행하세요.",
  "UninstallUWPForAll": "모든 사용자 대상",
  "UWPAppsTitle": "UWP 앱",
  "GraphicsPerformanceTitle": "선택한 앱의 그래픽 성능 설정을 \"고성능\"으로 설정하시겠습니까?",
  "ScheduledTaskPresented": "\"{0}\" 기능이 이미 \"{1}\"(으)로 생성되었습니다.",
  "CleanupTaskNotificationTitle": "Windows 정리",
  "CleanupTaskNotificationEvent": "Windows 사용하지 않는 파일 및 업데이트를 정리하는 작업을 실행하시겠습니까?",
  "CleanupTaskDescription": "기본 제공 디스크 정리 앱을 사용하여 Windows 사용하지 않는 파일 및 업데이트를 정리합니다. 예약된 작업은 사용자 \"{0}\"이(가) 시스템에 로그인한 경우에만 실행할 수 있습니다.",
  "CleanupNotificationTaskDescription": "Windows 사용하지 않는 파일 및 업데이트 정리에 대한 팝업 알림 리마인더입니다. 예약된 작업은 사용자 \"{0}\"이(가) 시스템에 로그인한 경우에만 실행할 수 있습니다.",
  "SoftwareDistributionTaskNotificationEvent": "Windows 업데이트 캐시가 성공적으로 삭제되었습니다.",
  "TempTaskNotificationEvent": "임시 파일 폴더가 성공적으로 정리되었습니다.",
  "FolderTaskDescription": "{0} 폴더 정리. 예약된 작업은 사용자 \"{0}\"이(가) 시스템에 로그인한 경우에만 실행할 수 있습니다.",
  "EventViewerCustomViewName": "프로세스 생성",
  "EventViewerCustomViewDescription": "프로세스 생성 및 명령줄 감사 이벤트.",
  "RestartWarning": "PC를 반드시 재시작하세요.",
  "ErrorsLine": "줄",
  "ErrorsMessage": "오류/경고",
  "DialogBoxOpening": "대화 상자를 표시하는 중...",
  "Disable": "비활성화",
  "Enable": "활성화",
  "AllFilesFilter": "모든 파일",
  "FolderSelect": "폴더 선택",
  "Suspend": "일시 중단",
  "Protect": "보호",
  "Configure": "구성",
  "FilesWontBeMoved": "파일이 이동되지 않습니다.",
  "Install": "설치",
  "Update": "업데이트/구성",
  "NoData": "표시할 내용이 없습니다.",
  "RestartFunction": "\"{0}\"을(를) 완료할 수 없습니다. 스크립트를 재시작한 후 이 조정을 다시 실행하세요.",
  "NoResponse": "{0}에 연결할 수 없습니다.",
  "Restore": "복원",
  "Run": "실행",
  "Skipped": "필수 구성 요소를 이 시스템에서 사용할 수 없으므로 \"{0}\"을(를) 건너뛰었습니다.",
  "GPOUpdate": "GPO를 업데이트하는 중...",
  "Uninstall": "제거",
  "GuiToggleStateEnabled": "활성화됨",
  "GuiToggleStateDisabled": "비활성화됨",
  "GuiExecutionPreparing": "준비 중...",
  "GuiExecutionWorking": "작업 중...",
  "GuiEmptyStateSearchNoResults": "현재 모든 탭에서 사용 가능한 조정이 없습니다.",
  "GuiEmptyStateSearchWithFilters": "모든 탭에서 활성 필터를 사용한 '{0}'과(와) 일치하는 조정이 없습니다.",
  "GuiEmptyStateSearchQueryOnly": "모든 탭에서 '{0}'과(와) 일치하는 조정이 없습니다.",
  "GuiEmptyStateTabFiltersOnly": "이 탭에서 활성 필터와 일치하는 조정이 없습니다.",
  "GuiEmptyStateTabSearchAndFilters": "이 탭에서 활성 필터를 사용한 '{0}'과(와) 일치하는 조정이 없습니다.",
  "GuiEmptyStateTabNoResults": "현재 이 탭에서 사용 가능한 조정이 없습니다.",
  "GuiEmptyStateTabQueryOnly": "이 탭에서 '{0}'과(와) 일치하는 조정이 없습니다.",
  "GuiPresetPanelHeading": "권장 선택 항목",
  "GuiScenarioModesHeading": "시나리오 모드",
  "GuiActiveFiltersHeading": "활성 필터",
  "GuiSelectAll": "모두 선택",
  "GuiUnselectAll": "모두 선택 해제",
  "GuiSystemScanButton": "시스템 검사",
  "GuiSystemScanEnabled": "시스템 검사가 활성화되었습니다.",
  "GuiHelpOpened": "도움말이 열렸습니다.",
  "GuiShowDetails": "세부 정보 표시",
  "GuiHideDetails": "세부 정보 숨기기",
  "GuiDetailsButton": "세부 정보",
  "GuiShowOptions": "옵션 표시",
  "GuiHideOptions": "옵션 숨기기",
  "GuiAbortButton": "중단",
  "GuiPauseButton": "일시 중지",
  "GuiExecutionSubheading": "진행 상황이 여기에 실시간으로 표시됩니다. 완료될 때까지 이 창을 열어 두세요.",
  "GuiResumeButton": "다시 시작",
  "GuiRunPaused": "실행 일시 중지됨...",
  "GuiRiskLevelLabel": "수준:",
  "GuiRiskLow": "낮은 위험",
  "GuiRiskMedium": "중간 위험",
  "GuiRiskHigh": "높은 위험",
  "GuiImpactBadge": "영향",
  "GuiTroubleshootingOnly": "문제 해결 전용",
  "GuiRestoreLabel": "복원:",
  "GuiRestorePossible": "가능",
  "GuiRestoreNotPossible": "불가능 - 이 변경은 영구적입니다",
  "GuiBehaviorLabel": "동작",
  "GuiDefaultLabel": "기본값",
  "GuiHelpTitle": "도움말",
  "GuiHelpSubtitle": "Baseline - 사용 가이드",
  "GuiLogViewerTitle": "로그 뷰어",
  "GuiRefreshButton": "새로 고침",
  "GuiOpenInNotepad": "메모장에서 열기",
  "GuiCloseButton": "닫기",
  "GuiLogSuccess": "성공",
  "GuiLogFailed": "실패",
  "GuiLogSkippedWarning": "건너뜀/경고",
  "GuiLogInfo": "정보",
  "GuiBuildProfile": "프로필 빌드",
  "GuiPreviewGameMode": "게임 모드 미리 보기",
  "GuiClearPlan": "계획 지우기",
  "GuiGameModeHeader": "게임 모드",
  "GuiExportSettings": "설정 내보내기",
  "GuiImportSettings": "설정 가져오기",
  "GuiDetectionFailed": "검색 실패",
  "GuiScanningSystem": "시스템 상태를 검사하는 중...",
  "GuiResetGamingTweaks": "게임 조정 초기화",
  "GuiBtnStartHere": "시작 가이드",
  "GuiBtnHelp": "도움말",
  "GuiBtnLog": "로그 열기",
  "GuiSearchLabel": "빠른 필터",
  "GuiSearchPlaceholder": "이름, 태그 또는 카테고리로 필터...",
  "GuiBtnClearSearch": "지우기",
  "GuiChkSafeMode": "안전 모드",
  "GuiChkLightMode": "라이트 모드",
  "GuiThemeDark": "테마: 다크",
  "GuiThemeLight": "테마: 라이트",
  "GuiBtnLanguage": "언어",
  "GuiBtnLanguageTooltip": "언어 변경",
  "GuiBtnFilterToggle": "필터",
  "GuiRiskFilterLabel": "위험도",
  "GuiCategoryFilterLabel": "카테고리",
  "GuiViewLabel": "보기",
  "GuiChkSelectedOnly": "선택된 항목만",
  "GuiChkHighRiskOnly": "높은 위험만",
  "GuiChkRestorableOnly": "복원 가능만",
  "GuiChkGamingOnly": "게임 관련",
  "GuiChkSelectedOnlyTip": "현재 GUI에서 선택된 조정만 표시합니다.",
  "GuiChkHighRiskOnlyTip": "높은 위험도의 조정만 표시합니다.",
  "GuiChkRestorableOnlyTip": "수동 복구가 필요한 조정을 숨깁니다.",
  "GuiChkGamingOnlyTip": "게임 성능, 호환성 또는 게임 품질과 관련된 조정을 표시합니다.",
  "GuiBtnDefaults": "Windows 기본값 복원",
  "GuiBtnPreviewRun": "미리보기",
  "GuiBtnRun": "조정 실행",
  "GuiExpertModeBanner": "전문가 모드 — 모든 프리셋과 고급 조정을 사용할 수 있습니다",
  "GuiExpertModeOn": "전문가 모드: 켜짐",
  "GuiTabInitialSetup": "초기 설정",
  "GuiTabPrivacyTelemetry": "개인정보 및 원격 측정",
  "GuiTabSecurity": "보안",
  "GuiTabSystem": "시스템",
  "GuiTabUIPersonalization": "UI 및 개인 설정",
  "GuiTabUWPApps": "UWP 앱",
  "GuiTabGaming": "게임",
  "GuiTabContextMenu": "컨텍스트 메뉴"
}
